{
  "accentColor": "{{appsmith.theme.colors.primaryColor}}",
  "alignWidget": "LEFT",
  "animateLoading": true,
  "borderRadius": "{{appsmith.theme.borderRadius.appBorderRadius}}",
  "bottomRow": 30,
  "defaultCheckedState": true,
  "displayName": "Checkbox",
  "dynamicBindingPathList": [
    {
      "key": "accentColor"
    },
    {
      "key": "borderRadius"
    }
  ],
  "dynamicHeight": "AUTO_HEIGHT",
  "hideCard": false,
  "iconSVG": "/static/media/icon.aaab032b43383e4fa53ffc0ef40c90ef.svg",
  "isDeprecated": false,
  "isDisabled": false,
  "isLoading": false,
  "isRequired": false,
  "isVisible": true,
  "key": "hsffvqo08b",
  "label": "Label",
  "labelPosition": "Left",
  "leftColumn": 3,
  "maxDynamicHeight": 9000,
  "minDynamicHeight": 4,
  "minWidth": 450,
  "mobileBottomRow": 30,
  "mobileLeftColumn": 3,
  "mobileRightColumn": 15,
  "mobileTopRow": 26,
  "parentColumnSpace": 18.49609375,
  "parentId": "r14k4o3qnn",
  "parentRowSpace": 10,
  "renderMode": "CANVAS",
  "responsiveBehavior": "fill",
  "rightColumn": 15,
  "searchTags": [
    "boolean"
  ],
  "topRow": 26,
  "type": "CHECKBOX_WIDGET",
  "version": 1,
  "widgetId": "zj0do38svq",
  "widgetName": "Checkbox1"
}